crewai_files/__init__.py
crewai_files/py.typed
crewai_files/cache/__init__.py
crewai_files/cache/cleanup.py
crewai_files/cache/metrics.py
crewai_files/cache/upload_cache.py
crewai_files/core/__init__.py
crewai_files/core/constants.py
crewai_files/core/resolved.py
crewai_files/core/sources.py
crewai_files/core/types.py
crewai_files/formatting/__init__.py
crewai_files/formatting/anthropic.py
crewai_files/formatting/api.py
crewai_files/formatting/bedrock.py
crewai_files/formatting/gemini.py
crewai_files/formatting/openai.py
crewai_files/processing/__init__.py
crewai_files/processing/constraints.py
crewai_files/processing/enums.py
crewai_files/processing/exceptions.py
crewai_files/processing/processor.py
crewai_files/processing/transformers.py
crewai_files/processing/validators.py
crewai_files/resolution/__init__.py
crewai_files/resolution/resolver.py
crewai_files/resolution/utils.py
crewai_files/uploaders/__init__.py
crewai_files/uploaders/anthropic.py
crewai_files/uploaders/base.py
crewai_files/uploaders/bedrock.py
crewai_files/uploaders/factory.py
crewai_files/uploaders/gemini.py
crewai_files/uploaders/openai.py
crewai_files-1.9.3.dist-info/METADATA
crewai_files-1.9.3.dist-info/WHEEL
crewai_files-1.9.3.dist-info/RECORD
