Metadata-Version: 2.4
Name: crewai-files
Version: 1.9.3
Summary: File handling utilities for CrewAI multimodal inputs
Author-email: Greyson LaLonde <greyson@crewai.com>
Requires-Python: <3.14,>=3.10
Requires-Dist: aiocache~=0.12.3
Requires-Dist: aiofiles~=24.1.0
Requires-Dist: av~=13.0.0
Requires-Dist: pillow~=10.4.0
Requires-Dist: pypdf~=4.0.0
Requires-Dist: python-magic>=0.4.27
Requires-Dist: tinytag~=1.10.0
